{
  "case_study_sentence": "Cassandra: from governance infrastructure to evidence infrastructure.",
  "caveat": "Public observatory data for Cassandra structural observation only; not trusted-list validation, legal-status determination, supervision, signature validation, relying-party processing, or public alerting.",
  "data": {
    "date": "2026-05-30",
    "package_path": "evidence/2026-05-30/cassandra-observation.aep",
    "package_sha256": "e6cf0b11a475cdfe1fed766cb2926c91d2d31027c7e9b7e53ab979ce045e56a4",
    "public_package": {
      "path": "evidence/2026-05-30/cassandra-observation.aep",
      "sha256": "e6cf0b11a475cdfe1fed766cb2926c91d2d31027c7e9b7e53ab979ce045e56a4",
      "size_bytes": 12627
    },
    "public_receipt": {
      "path": "evidence/2026-05-30/eatf-verification.json",
      "sha256": "d57f0a4ba79fe0da5917181743557307244052f8ddd451206c9354d0c6250d15",
      "size_bytes": 3587
    },
    "receipt_path": "evidence/2026-05-30/eatf-verification.json",
    "receipt_sha256": "d57f0a4ba79fe0da5917181743557307244052f8ddd451206c9354d0c6250d15",
    "signing_profile": "local-dev:eatf-dev-rsa4096",
    "status": "ok",
    "valid": true,
    "verifier_url": "https://eatf.eu/verify"
  },
  "id": "eatf-receipt",
  "interpretation": "A status of ok verifies package bytes, envelope structure, and declared hashes only.",
  "not_a": "trusted-list validation; legal-status determination; signature validation; supervision; compliance judgment; relying-party processing; public alerting; publication approval",
  "project": "cassandra",
  "schema": "urn:tyche:cassandra:observatory-card:0.1",
  "summary": "Latest EATF/AEP receipt status for the Cassandra evidence package.",
  "title": "EATF receipt boundary"
}
