{
  "accessed": "2026-06-11T04:58:40.796066+00:00",
  "bytes": 15458561,
  "completed": "2026-06-11T04:58:43.046416+00:00",
  "content_length_header": "15458561",
  "content_type": "application/pdf",
  "destination": "/home/runner/work/cassandra/cassandra/snapshots/2026-06-11/06-cz.pdf",
  "final_url": "https://tsl.gov.cz/publ/TSL_CZ.pdf",
  "http_status": 200,
  "redirect_count": 0,
  "redirect_history": [],
  "research_caveat": "Raw public snapshot for structural observation only; not relying-party validation or legal-status determination.",
  "sha256": "6bd28729470154101548edcd50136a30296e1ce3d069f778a0f7ef18081c8368",
  "url": "https://tsl.gov.cz/publ/TSL_CZ.pdf"
}
