{
  "accessed": "2026-05-21T21:16:24.391729+00:00",
  "bytes": 253737,
  "completed": "2026-05-21T21:16:24.513965+00:00",
  "content_length_header": "253737",
  "content_type": "text/xml",
  "destination": "/home/anton/projects/cassandra/snapshots/2026-05-22/31-lv.xml",
  "http_status": 200,
  "research_caveat": "Raw public XML snapshot for structural observation only; not relying-party validation or legal-status determination.",
  "sha256": "406073daa0dcf04670002803ad91026001d85274da64a9264739027d88566be1",
  "url": "https://trustlist.gov.lv/tsl/latvian-tsl.xml"
}
