{
  "artifact_paths": {
    "baseline": "baselines/2026-05-31.json",
    "diff": "diffs/2026-05-31.json",
    "normalized_manifest": "normalized/2026-05-31/manifest.json",
    "snapshot_manifest": "snapshots/2026-05-31/manifest.json"
  },
  "caveats": [
    "This artifact does not perform relying-party validation, signature verification, supervision, legal-status determination, public alerting, or publication readiness assessment.",
    "Fetch failures, parser results, and diffs are operational or structural observations only.",
    "Listed names are intentionally not reproduced in prose; detailed machine-readable snapshot files remain local workspace artifacts."
  ],
  "counts": {
    "baseline_created": false,
    "diff_change_count": 0,
    "diff_current_record_count": 31,
    "fetch_errors": 2,
    "fetched_content_files": 41,
    "normalization_errors": 1,
    "normalization_inputs": 41,
    "normalization_skips": 9,
    "normalized_xml_artifacts": 31,
    "pointer_attempts": 43,
    "provider_inventory_changed": 0,
    "provider_service_detail_changed": 0,
    "service_inventory_changed": 0
  },
  "created_at": "2026-05-31T04:57:05.782218Z",
  "date": "2026-05-31",
  "hashes": {
    "baseline_sha256": "3f043f3432bd94d0ca3a19e803f75ce2cdb6e00ef64801b2bcdbf8bda0f9b36b",
    "diff_sha256": "26abea9ad55924303a2eb2756187bc01473f0086dd70b89883237e7601a06ef7",
    "normalized_manifest_sha256": "a3bf590e3bb4843e5c2b0c6f27a83b6d61e9ced85c03d1e255751b75135333a2",
    "pointers_sha256": "8de007e4954d3410e95dfad25bac4019125156c42af80e229747997fa5db7600",
    "snapshot_manifest_sha256": "d73e170440b0c2b626f05d1c84649a6248c9cf3f413667f071d098c12db2a33f"
  },
  "inputs": {
    "lotl_url": "https://ec.europa.eu/tools/lotl/eu-lotl.xml",
    "pointers_file": "notes/pointers.json"
  },
  "schema": "urn:tyche:cassandra:snapshot-summary:0.2",
  "scope": "Research-only structural observation of public LOTL-derived trusted-list snapshots.",
  "workspace": "/home/runner/work/cassandra/cassandra"
}
